finorch/__init__.py
finorch/client/__init__.py
finorch/client/client.py
finorch/config/__init__.py
finorch/config/config.py
finorch/sessions/__init__.py
finorch/sessions/abstract_client.py
finorch/sessions/abstract_session.py
finorch/sessions/abstract_wrapper.py
finorch/sessions/cit/__init__.py
finorch/sessions/cit/client.py
finorch/sessions/cit/session.py
finorch/sessions/cit/wrapper.py
finorch/sessions/database.py
finorch/sessions/local/__init__.py
finorch/sessions/local/client.py
finorch/sessions/local/session.py
finorch/sessions/local/wrapper.py
finorch/sessions/ozstar/__init__.py
finorch/sessions/ozstar/client.py
finorch/sessions/ozstar/session.py
finorch/sessions/ozstar/wrapper.py
finorch/sessions/ssh/__init__.py
finorch/sessions/ssh/session.py
finorch/transport/__init__.py
finorch/transport/abstract_transport.py
finorch/transport/exceptions.py
finorch/transport/local.py
finorch/transport/ssh.py
finorch/utils/__init__.py
finorch/utils/cd.py
finorch/utils/job_status.py
finorch/utils/port.py
finorch/utils/xmlrpc.py
finorch/wrapper/__init__.py
finorch/wrapper/wrapper.py
finorch-0.2.0.dist-info/entry_points.txt
finorch-0.2.0.dist-info/LICENSE
finorch-0.2.0.dist-info/WHEEL
finorch-0.2.0.dist-info/METADATA
finorch-0.2.0.dist-info/RECORD
