Metadata-Version: 2.1
Name: finorch
Version: 0.2.0
Summary: Finesse version 3 job orchestrator and manager. This package can be used to run parallel jobs on various remote platforms, as well as locally.
Author: Lewis Lakerink
Author-email: llakerink@swin.edu.au
Requires-Python: >=3.8,<4.0
Classifier: Programming Language :: Python :: 3
Classifier: Programming Language :: Python :: 3.10
Classifier: Programming Language :: Python :: 3.8
Classifier: Programming Language :: Python :: 3.9
Provides-Extra: htcondor
Requires-Dist: SQLAlchemy (>=1.4.29,<2.0.0)
Requires-Dist: appdirs (>=1.4.4,<2.0.0)
Requires-Dist: exc (>=0.92,<0.93)
Requires-Dist: finesse (>=3.0a2,<4.0)
Requires-Dist: htcondor (>=9.5.0,<10.0.0); extra == "htcondor"
Requires-Dist: paramiko (>=2.9.2,<3.0.0)
Requires-Dist: section (>=2.0,<3.0)
